pyft232h/__init__.py
pyft232h/ft232h.py
pyft232h-1.0.1.dist-info/LICENSE
pyft232h-1.0.1.dist-info/METADATA
pyft232h-1.0.1.dist-info/WHEEL
pyft232h-1.0.1.dist-info/top_level.txt
pyft232h-1.0.1.dist-info/RECORD
