Metadata-Version: 2.2
Name: pyft232h
Version: 1.0.1
Summary: A SPI driver interface for ft232h with MPSSE
Author-email: VenkataDurgaPrasad <venkatadp421@gmail.com>
Maintainer-email: VenkataDurgaPrasad <venkatadp421@gmail.com>
Project-URL: Homepage, https://github.com/VenkataDP/pyft232h
Project-URL: Issues, https://github.com/VenkataDP/pyft232h/issues
Keywords: ft232h,c232hm,spi_mpsse
Classifier: Programming Language :: Python :: 3
Classifier: Operating System :: OS Independent
Classifier: License :: OSI Approved :: MIT License
Requires-Python: >=3.8
License-File: LICENSE
Requires-Dist: ftd2xx
